Seq.v
/*Summary:
This project implements a Sequence Detector using a Finite State
 Machine (FSM) in Verilog. It aims to detect a specific input
sequence and generate an output based on the current state. 
The design includes a Sequence Detector module with sequential
 memory and combinational logic to determine the next state
  and output.
*/

module Sequence_Detector_MOORE_Verilog(
  sequence_in, // binary input
  clock,       // clock signal
  reset,       // reset input
  detector_out // output of the sequence detector
);
  input clock;                     // clock signal
  input reset;                     // reset input
  input sequence_in;               // binary input
  output reg detector_out;         // output of the sequence detector
  
  parameter Zero = 4'b0000,        // "Zero" State
            One = 4'b0001,         // "One" State
            OneZero = 4'b0010,     // "OneZero" State
            OneZeroZero = 4'b0100, // "OneZeroZero" State
            OneZeroZeroOne = 4'b1001; // "OneZeroZeroOne" State
  
  reg [3:0] current_state, next_state; // current state and next state
  
  // Sequential memory of the Finite State Machine
  always @(posedge clock, posedge reset)
  begin
  
    if (reset == 1) 
      current_state <= Zero;    // When reset = 1, reset the state of the Finite State Machine to "Zero" State
    else
      current_state <= next_state; // Otherwise, transition to the next state
  end
  
  always @(current_state, sequence_in)
  begin
    case (current_state)
      Zero:
        begin
          // Transition from "Zero" state
          // If sequence_in is 1, transition to "One" state
          // Otherwise, remain in "Zero" state
          if (sequence_in == 1)
            next_state = One;
          else
            next_state = Zero;
        end
      One:
        begin
          // Transition from "One" state
          // If sequence_in is 0, transition to "OneZero" state
          // Otherwise, remain in "One" state
          if (sequence_in == 0)
            next_state = OneZero;
          else
            next_state = One;
        end
      OneZero:
        begin
          // Transition from "OneZero" state
          // If sequence_in is 0, transition to "OneZeroZero" state
          // Otherwise, remain in "One" state
          if (sequence_in == 0)
            next_state = OneZeroZero;
          else
            next_state = One;
        end
      OneZeroZero:
        begin
          // Transition from "OneZeroZero" state
          // If sequence_in is 0, transition to "Zero" state
          // Otherwise, transition to "OneZeroZeroOne" state
          if (sequence_in == 0)
            next_state = Zero;
          else
            next_state = OneZeroZeroOne;
        end
      OneZeroZeroOne:
        begin
          // Transition from "OneZeroZeroOne" state
          // If sequence_in is 0, transition to "OneZero" state
          // Otherwise, remain in "One" state
          if (sequence_in == 0)
            next_state = OneZero;
          else
            next_state = One;
        end
      default:
        next_state = Zero;
    endcase
  end
  
  // Combinational logic to determine the output of the Finite State Machine
  // The output only depends on the current state
  always @(current_state)
  begin
    case (current_state)
      Zero:
        detector_out = 0;
      One:
        detector_out = 0;
      OneZero:
        detector_out = 0;
      OneZeroZero:
        detector_out = 0;
      OneZeroZeroOne:
        detector_out = 1;
      default:
        detector_out = 0;
    endcase
  end
endmodule

Seq_tb.v
`include "Seq.v"
module tb_Sequence_Detector_Moore_FSM_Verilog;

  // Inputs
  reg sequence_in;   // Input sequence
  reg clock;         // Clock signal
  reg reset;         // Reset signal

  // Outputs
  wire detector_out; // Output of the sequence detector

  parameter CLK_PERIOD = 10; // Clock period in time units

  // Instantiate the Sequence Detector using Moore FSM
  Sequence_Detector_MOORE_Verilog uut (
    .sequence_in(sequence_in),
    .clock(clock),
    .reset(reset),
    .detector_out(detector_out)
  ); 

  always #((CLK_PERIOD)/2) clock = ~clock;

  initial begin
    clock = 0;

  end 

  initial begin
    // Initialize Inputs
    $dumpfile("Seq_tb.vcd");
    $dumpvars(0, tb_Sequence_Detector_Moore_FSM_Verilog);

    sequence_in = 0;
    reset = 1;

    // Wait 100 ns for global reset to finish
    #10;
    reset = 0;

    #40;
    sequence_in = 1;
    #10;
    sequence_in = 0;
    #10;
    sequence_in = 1; 
    #10;
    sequence_in = 0; 
    #10;
    sequence_in = 0; 
    #10;
    sequence_in = 1;  
    #10;
    sequence_in = 1;  
    #10;
    sequence_in = 0;
    #10;
    sequence_in = 1;
    #10;
    sequence_in = 0; 
    #10;
    sequence_in = 0; 
    #10;
    sequence_in = 1; 
    #10;
    sequence_in = 1;  
    #10;
    sequence_in = 0;  
    #10;

    $finish;
  end
endmodule

Seq_tb.vcd
$date
	Tue Jun 20 17:28:13 2023
$end
$version
	Icarus Verilog
$end
$timescale
	1s
$end
$scope module tb_Sequence_Detector_Moore_FSM_Verilog $end
$var wire 1 ! detector_out $end
$var parameter 32 " CLK_PERIOD $end
$var reg 1 # clock $end
$var reg 1 $ reset $end
$var reg 1 % sequence_in $end
$scope module uut $end
$var wire 1 # clock $end
$var wire 1 $ reset $end
$var wire 1 % sequence_in $end
$var parameter 4 & One $end
$var parameter 4 ' OneZero $end
$var parameter 4 ( OneZeroZero $end
$var parameter 4 ) OneZeroZeroOne $end
$var parameter 4 * Zero $end
$var reg 4 + current_state [3:0] $end
$var reg 1 ! detector_out $end
$var reg 4 , next_state [3:0] $end
$upscope $end
$upscope $end
$enddefinitions $end
$comment Show the parameter values. $end
$dumpall
b0 *
b1001 )
b100 (
b10 '
b1 &
b1010 "
$end
#0
$dumpvars
b0 ,
b0 +
0%
1$
0#
0!
$end
#5
1#
#10
0#
0$
#15
1#
#20
0#
#25
1#
#30
0#
#35
1#
#40
0#
#45
1#
#50
b1 ,
0#
1%
#55
b1 +
1#
#60
b10 ,
0#
0%
#65
b100 ,
b10 +
1#
#70
b1 ,
0#
1%
#75
b1 +
1#
#80
b10 ,
0#
0%
#85
b100 ,
b10 +
1#
#90
0#
#95
b0 ,
b100 +
1#
#100
b1001 ,
0#
1%
#105
1!
b1 ,
b1001 +
1#
#110
0#
#115
0!
b1 +
1#
#120
b10 ,
0#
0%
#125
b100 ,
b10 +
1#
#130
b1 ,
0#
1%
#135
b1 +
1#
#140
b10 ,
0#
0%
#145
b100 ,
b10 +
1#
#150
0#
#155
b0 ,
b100 +
1#
#160
b1001 ,
0#
1%
#165
1!
b1 ,
b1001 +
1#
#170
0#
#175
0!
b1 +
1#
#180
b10 ,
0#
0%
#185
b100 ,
b10 +
1#
